CHANGELOG.txt
KLS_start.py
LICENSE
README.md
setup.py
test.py
KeyloggerScreenshot/Keylogger_Target.py
KeyloggerScreenshot/Port_data.py
KeyloggerScreenshot/Server_keylogger.py
KeyloggerScreenshot/Server_listener.py
KeyloggerScreenshot/Server_photos.py
KeyloggerScreenshot/Server_timer.py
KeyloggerScreenshot/Simulation_code.py
KeyloggerScreenshot/__init__.py
KeyloggerScreenshot.egg-info/PKG-INFO
KeyloggerScreenshot.egg-info/SOURCES.txt
KeyloggerScreenshot.egg-info/dependency_links.txt
KeyloggerScreenshot.egg-info/requires.txt
KeyloggerScreenshot.egg-info/top_level.txt