Metadata-Version: 2.1
Name: KeyloggerScreenshot
Version: 0.6.2.1
Summary: Exporting Keylogger files, recording audio, recording mouse click information and screenshots of the target. For more information check out my website:https://pypi.org/project/KeyloggerScreenshot/ and my github: https://github.com/Facileee/KeyloggerScreenshot
Home-page: 
Author: Fawaz Bashiru
Author-email: fawazbashiru@gmail.com
License: MIT
Keywords: Keylogger
Classifier: Development Status :: 6 - Mature
Classifier: Intended Audience :: Education
Classifier: Operating System :: Microsoft :: Windows :: Windows 10
Classifier: License :: OSI Approved :: MIT License
Classifier: Programming Language :: Python :: 3
License-File: LICENSE
